classProjectStuff/232/Project2/lab/boxdriver.vhd
-- Quartus II VHDL Template
-- Unsigned Adder

library ieee;
use ieee.std_logic_1164.all;
use ieee.numeric_std.all;

entity boxdriver is

	port 
	(
		a	   : in std_logic_vector  (3 downto 0);
		result : out std_logic_vector (3 downto 0)
	);

end entity;

architecture rtl of boxdriver is
begin

    result(0) <= '1' when a = "0000" or a = "0001" or a = "0010" or a = "0011" else '0';
    result(1) <= '1' when a = "0100" or a = "0101" or a = "0110" or a = "0111" else '0';
    result(2) <= '1' when a = "1000" or a = "1001" or a = "1010" or a = "1011" else '0'; 
    result(3) <= '1' when a = "1100" or a = "1101" or a = "1110" or a = "1111" else '0'; 


end rtl;

classProjectStuff/232/Project2/lab/boxtest.vhd
-- Bruce Maxwell
-- Spring 2015
-- CS 232 Project 2
--

library ieee;
use ieee.std_logic_1164.all;

entity boxtest is
end entity;

architecture test of boxtest is
  signal A: std_logic_vector(3 downto 0);
  signal Aout: std_logic_vector(3 downto 0);

  component boxdriver
  port(
  A: in std_logic_vector(3 downto 0);
  result: out std_logic_vector(3 downto 0)
  );
  end component;
    
  begin

    A(3) <= '0', '1' after 200 ns, '0' after 400 ns;
    A(2) <= '0', '1' after 100 ns, '0' after 200 ns, '1' after 300 ns;
    A(1) <= '0', '1' after 50 ns, '0' after 100 ns, '1' after 150 ns, '0' after 200 ns, '1' after 250 ns, '0' after 300 ns, '1' after 350 ns;
    A(0) <= '0', '1' after 25 ns, '0' after 50 ns, '1' after 75 ns, '0' after 100 ns, '1' after 125 ns, '0' after 150 ns, '1' after 175 ns, '0' after 200 ns, '1' after 225 ns, '0' after 250 ns, '1' after 275 ns, '0' after 300 ns , '1' after 325 ns, '0' after 350 ns, '1' after 375 ns;

    C0: boxdriver port map( A, Aout );

  end test;

classProjectStuff/232/Project2/lab/boxtest.vcd
$date
  Sun Sep 20 10:08:29 2020
$end
$version
  GHDL v0
$end
$timescale
  1 fs
$end
$scope module standard $end
$upscope $end
$scope module std_logic_1164 $end
$upscope $end
$scope module numeric_std $end
$upscope $end
$scope module boxtest $end
$var reg 4 ! a[3:0] $end
$var reg 4 " aout[3:0] $end
$scope module c0 $end
$var reg 4 # a[3:0] $end
$var reg 4 $ result[3:0] $end
$upscope $end
$upscope $end
$enddefinitions $end
#0
b0000 !
b0001 "
b0000 #
b0001 $
#25000000
b0001 !
b0001 #
#50000000
b0010 !
b0010 #
#75000000
b0011 !
b0011 #
#100000000
b0100 !
b0010 "
b0100 #
b0010 $
#125000000
b0101 !
b0101 #
#150000000
b0110 !
b0110 #
#175000000
b0111 !
b0111 #
#200000000
b1000 !
b0100 "
b1000 #
b0100 $
#225000000
b1001 !
b1001 #
#250000000
b1010 !
b1010 #
#275000000
b1011 !
b1011 #
#300000000
b1100 !
b1000 "
b1100 #
b1000 $
#325000000
b1101 !
b1101 #
#350000000
b1110 !
b1110 #
#375000000
b1111 !
b1111 #
#400000000
b0111 !
b0010 "
b0111 #
b0010 $
