classProjectStuff/232/Project5/pldrom.vhd
-- Owen Goldthwaite
-- CS232

library ieee;
use ieee.std_logic_1164.all;
use ieee.numeric_std.all;

entity pldrom is
  port 
  (
    addr  : in std_logic_vector (3 downto 0);
    data  : out std_logic_vector (9 downto 0)
  );

end entity;

architecture rtl of pldrom is
  -- definitions go here

begin
-- Given Test 1
--   data <= 
--     "0001100000" when addr = "0000" else -- move 0s to LR   00000000/00000000
--     "0001110000" when addr = "0001" else -- move 1s to LR   11111111/00000000
--     "0001101010" when addr = "0010" else -- move 1010 to LR 11111010/00000000
--     "0010101000" when addr = "0011" else -- move 8 to ACC   11111010/00001000
--     "0101001100" when addr = "0100" else -- shift LR left   
--     "0100011000" when addr = "0101" else -- add -1 to ACC  
--     "1100001000" when addr = "0110" else -- branch if  zero  
--     "1000000100" when addr = "0111" else -- branch  
--     "0001110000" when addr = "1000" else -- set LR to 1s    11111111/00000000
--     "1000000000" when addr = "1001" else -- branch to zero  11111111/00000000
--     "0101010101" when addr = "1010" else -- garbage
--     "1010101010" when addr = "1011" else -- garbage
--     "1100110011" when addr = "1100" else -- garbage
--     "0011001100" when addr = "1101" else -- garbage
--     "0000000000" when addr = "1110" else -- garbage
--     "1111111111";                        -- garbage

-- -- Given Test 2, operator test
-- data <= 
-- "0001110000" when addr = "0000" else -- move 11111111 to the LR    
-- "0011100000" when addr = "0001" else -- move 0000 from the IR to the high 4 bits of the ACC
-- "0010100010" when addr = "0010" else -- move 0010 from the IR to the low 4 bits of the ACC
-- "0100000100" when addr = "0011" else -- Add ACC to LR and put it back into the LR
-- "0100000100" when addr = "0100" else -- Add ACC to LR and put it back into the LR
-- "0100100100" when addr = "0101" else -- Subtract ACC from LR and put it back into the LR
-- "0101001100" when addr = "0110" else -- Shift the LR left and write it back to the LR
-- "0101101100" when addr = "0111" else -- Shift the LR right and write it back to the LR
-- "0111101100" when addr = "1000" else -- Rotate the LR right and write it back to the LR
-- "0101101100" when addr = "1001" else -- Shift the LR right and write it back to the LR
-- "0110011100" when addr = "1010" else -- XOR the LR with all 1s and write it back to the LR (bit inversion)
-- "0110110101" when addr = "1011" else -- AND the LR with 01 (sign-extended)
-- "0100010110" when addr = "1100" else -- ADD the LR with 10 (sign-extended)
-- "1111111111";                        -- garbage

-- Third instruction set, counting down and flash thing
-- data <= 
-- "0011100001" when addr = "0000" else -- ACC gets 0001 in 4 high bits 00000000 / 00010000
-- "0001000000" when addr = "0001" else -- LR gets ACC value            00010000 / 00010000
-- "0011100000" when addr = "0010" else -- ACC high bits get 0000       00010000 / 00000000
-- "0010100001" when addr = "0011" else -- ACC low bits get 0001        00010000 / 00000001
-- "0100100100" when addr = "0100" else -- LR gets LR - ACC (ACC = 1)   00001111 / 00000001
-- "1110000111" when addr = "0101" else -- Branch to 0111 if LR is 0, break from loop
-- "1000000100" when addr = "0110" else -- Branch to 0100 to continue loop 
-- "0010100001" when addr = "0111" else -- ACC low bits get 0001        00000000 / 00000001
-- "0001110000" when addr = "1000" else -- Set LR to all 1s             11111111 / 00000001
-- "0001100000" when addr = "1001" else -- Set LR to all 0s             00000000 / 00000001
-- "0101000000" when addr = "1010" else -- Shift ACC left by one bit    00000000 / 00000010
-- "1100001101" when addr = "1011" else -- Branch to 1101 if ACC is 0, break from loop
-- "1000001000" when addr = "1100" else -- Branch to 1000 to continue loop 
-- "1000000000" when addr = "1101" else -- Branch to 0000 to restart 
-- "1111111111";                        -- TRASH

-- -- Fourth cucstom instruction set
data <= 
"0010100001" when addr = "0000" else -- ACC gets 0001 in 4 low  bits 00000000 / 00000001
"0100000100" when addr = "0001" else -- LR gets LR + ACC             00000001 / 00000001
"1111000100" when addr = "0010" else -- Branch to 0100 if LR = 8, break from loop
"1000000001" when addr = "0011" else -- Branch to 0001, loop               
"0001110000" when addr = "0100" else -- LR gets all 1s               11111111 / 00000001
"0101101100" when addr = "0101" else -- Shift LR right by one bit    01111111 / 00000001
"0101101100" when addr = "0110" else -- Shift LR right by one bit    00111111 / 00000001
"0101101100" when addr = "0111" else -- Shift LR right by one bit    00011111 / 00000001
"0100100100" when addr = "1000" else -- LR gets LR - ACC (ACC = 1)   11111110 / 00000001
"1111001011" when addr = "1001" else -- Branch to 1011 if LR = 8, break from loop
"1000001000" when addr = "1010" else -- Branch to 1000, loop  
"0001100000" when addr = "1011" else -- Set LR to all 0s             00000000 / 00000001
"1000000000" when addr = "1100" else -- Branch to 0000 to restart 
"1111111111";                        -- TRASH






end rtl;

classProjectStuff/232/Project5/pld2.vhd
-- Owen Goldthwaite
-- CS232

library ieee;
use ieee.std_logic_1164.all;
use ieee.numeric_std.all;

entity pld2 is

	port(
		clk		 : in	std_logic;
		reset	 : in	std_logic;
        lights	 : out	std_logic_vector(7 downto 0);
        IRView	 : out	std_logic_vector(9 downto 0)      
	);

end entity;

architecture rtl of pld2 is

    component pldrom is
        port 
        (
          addr  : in std_logic_vector (3 downto 0);
          data  : out std_logic_vector (9 downto 0)
        );
    end component;

	-- Build an enumerated type for the state machine
	type state_type is (sFetch, sExecute1, sExecute2);
	-- Register to hold the current state
    signal state   : state_type;
    -- Other signals
    signal IR : std_logic_vector(9 downto 0);
    signal ROMvalue : std_logic_vector(9 downto 0);
    signal PC : unsigned(3 downto 0);
    signal LR : unsigned(7 downto 0);
    signal ACC : unsigned(7 downto 0);
    signal SRC : unsigned(7 downto 0);


begin

	-- Logic to advance to the next state
	process (clk, reset)
	begin
        if reset = '0' then
            -- Resetting everything
            LR <= (others => '0'); 
            PC <= (others => '0');
            IR <= (others => '0');
            ACC <= (others => '0');
            SRC <= (others => '0');
            state <= sFetch;
		elsif (rising_edge(clk)) then
			case state is
				when sFetch=>
                    IR <= ROMvalue;
                    PC <= PC + 1;
                    state <= sExecute1;
                when sExecute1=> 
                    case IR(9 downto 8) is --C1C0 bits for definding operation type
                        when "00" => -- Move conditions
                            case IR(5 downto 4) is -- Move SRC assigning
                                when "00" => SRC <= ACC; -- SRC gets ACC
                                when "01" => SRC <= LR; -- SRC gets LR
                                when "10" => 
                                    if IR(3) = '0' then
                                        SRC <= "0000" & unsigned(IR(3 downto 0)); -- SRC gets low 4 IR bits, sign extending 0
                                    else
                                        SRC <= "1111" & unsigned(IR(3 downto 0)); -- SRC gets low 4 IR bits, sign extending 1
                                    end if;
                                when "11" => SRC <= "11111111"; -- SRC gets all 1s
                                when others => null;
                            end case;
                        when "01" => -- Binary Operator SRC assigning
                            case IR(4 downto 3) is
                                when "00" => SRC <= ACC; -- SRC gets ACC
                                when "01" => SRC <= LR;  -- SRC gets LR
                                when "10" => 
                                    if IR(3) = '0' then
                                        SRC <= "000000" & unsigned(IR(1 downto 0)); -- SRC gets low 4 IR bits, sign extending 0
                                    else
                                        SRC <= "111111" & unsigned(IR(1 downto 0)); -- SRC gets low 4 IR bits, sign extending 1
                                    end if;
                                when "11" => SRC <= "11111111"; -- SRC gets all 1s
                                when others => null;
                            end case;
                        when "10" => -- Unconditional Branch
                            PC <= unsigned(IR(3 downto 0)); -- PC gets 4 address bits
                        when "11" => -- Conditional Branch
                            case IR(7) is 
                                when '0' => -- When checking against ACC 
                                    if IR(6) = '1' then
                                        if ACC = "00001000" then -- Extension Branch, if = 8
                                            PC <= unsigned(IR(3 downto 0)); -- Branch
                                        end if;
                                    elsif ACC = "00000000" then -- If 0
                                        PC <= unsigned(IR(3 downto 0)); -- Branch
                                    end if;
                                when '1' => -- When checking aginst LR
                                    if IR(6) = '1' then
                                        if LR = "00001000" then -- Extension Branch, if = 8
                                            PC <= unsigned(IR(3 downto 0)); -- Branch
                                        end if;
                                    elsif LR = "00000000" then -- If 0
                                        PC <= unsigned(IR(3 downto 0)); -- Branch
                                    end if;
                                when others => null;
                            end case;
                        when others => null;
                    end case;
                    state <= sExecute2; -- Setting to sExecute2 
                when sExecute2=>
                    case IR(9 downto 8) is --C1C0 bits for defining operation type
                    when "00" => -- Move conditions
                        case IR(7 downto 6) is -- Move SRC assigning
                            when "00" => ACC <= SRC; -- ACC gets SRC
                            when "01" => LR <= SRC; -- LR gets SRC
                            when "10" => ACC(3 downto 0) <= SRC(3 downto 0); -- Low ACC bits getting low SRC bits
                            when "11" => ACC(7 downto 4) <= SRC(3 downto 0); -- High ACC bits getting low SRC bits
                            when others => null;
                        end case;
                    when "01" => -- Binary Operator 
                        case IR(2) is
                            when '0' => -- Assigning to ACC
                                case IR(7 downto 5) is
                                    when "000" => ACC <= ACC + SRC; -- Dest gets Dest + SRC
                                    when "001" => ACC <= ACC - SRC; -- Dest gets Dest - SRC
                                    when "010" => ACC <= shift_left(SRC,1); -- Dest gets SRC shifted 1 left
                                    when "011" => ACC <= shift_right(SRC,1); -- Dest gets SRC shifted 1 right, add sign bit maintaining
                                    when "100" => ACC <= ACC xor SRC; -- Dest gets Dest xor SRC
                                    when "101" => ACC <= ACC and SRC; -- Dest gets Dest and SRC
                                    when "110" => ACC <= rotate_left(SRC,1); -- Dest gets SRC rotated left 1
                                    when "111" => ACC <= rotate_right(SRC,1); -- Dest gets SRC rotated right 1
                                    when others => null;
                                end case;
                            when '1' => -- Assigning to LR
                                case IR(7 downto 5) is
                                    when "000" => LR <= LR + SRC; -- Dest gets Dest + SRC
                                    when "001" => LR <= LR - SRC; -- Dest gets Dest - SRC
                                    when "010" => LR <= shift_left(SRC,1); -- Dest gets SRC shifted 1 left
                                    when "011" => LR <= shift_right(SRC,1); -- Dest gets SRC shifted 1 right, add sign bit maintaining
                                    when "100" => LR <= LR xor SRC; -- Dest gets Dest xor SRC
                                    when "101" => LR <= LR and SRC; -- Dest gets Dest and SRC
                                    when "110" => LR <= rotate_left(SRC,1); -- Dest gets SRC rotated left 1
                                    when "111" => LR <= rotate_right(SRC,1); -- Dest gets SRC rotated right 1
                                    when others => null;
                                end case;
                            when others => null;                            
                        end case;
                    when others => null;
                end case;
                    state <= sFetch; -- Setting state back to fetch, get next IR 
			end case;
		end if;
    end process;
    
    IRview <= IR;
    lights <= std_logic_vector(LR);

    pldrom1: pldrom port map(addr=>std_logic_vector(PC), data=>ROMvalue);

end rtl;

classProjectStuff/232/Project5/pldbench.vhd
-- Bruce A. Maxwell
-- Spring 2013
-- CS 232
--
-- test program for the lights circuit
--

library ieee;
use ieee.std_logic_1164.all;
use ieee.numeric_std.all;

entity pldbench is
end entity;

architecture test of pldbench is
  constant num_cycles : integer := 1000;

  -- this circuit just needs a clock and a reset
  signal clk : std_logic := '1';
  signal reset : std_logic;

  -- lights component
  component pld2
    port( clk, reset : in std_logic;
          lights     : out std_logic_vector(7 downto 0);
          IRView     : out std_logic_vector(9 downto 0) );
  end component;

  -- output signals
  signal lightsig : std_logic_vector(7 downto 0);
  signal irview : std_logic_vector(9 downto 0);

begin

  -- start off with a short reset
  reset <= '0', '1' after 5 ns;

  -- create a clock
  process begin
    for i in 1 to num_cycles loop
      clk <= not clk;
      wait for 2 ns;
      clk <= not clk;
      wait for 2 ns;
    end loop;
    wait;
  end process;

  -- port map the circuit
  L0: pld2 port map( clk, reset, lightsig, irview );

end test;

classProjectStuff/232/Project5/pldbench.vcd
$date
  Mon Oct 19 13:57:45 2020
$end
$version
  GHDL v0
$end
$timescale
  1 fs
$end
$scope module standard $end
$upscope $end
$scope module std_logic_1164 $end
$upscope $end
$scope module numeric_std $end
$upscope $end
$scope module pldbench $end
$var reg 1 ! clk $end
$var reg 1 " reset $end
$var reg 8 # lightsig[7:0] $end
$var reg 10 $ irview[9:0] $end
$scope module l0 $end
$var reg 1 % clk $end
$var reg 1 & reset $end
$var reg 8 ' lights[7:0] $end
$var reg 10 ( irview[9:0] $end
$comment state is not handled $end
$var reg 10 ) ir[9:0] $end
$var reg 10 * romvalue[9:0] $end
$var reg 4 + pc[3:0] $end
$var reg 8 , lr[7:0] $end
$var reg 8 - acc[7:0] $end
$var reg 8 . src[7:0] $end
$scope module pldrom1 $end
$var reg 4 / addr[3:0] $end
$var reg 10 0 data[9:0] $end
$upscope $end
$upscope $end
$upscope $end
$enddefinitions $end
#0
0!
0"
b00000000 #
b0000000000 $
0%
0&
b00000000 '
b0000000000 (
b0000000000 )
b0001110000 *
b0000 +
b00000000 ,
b00000000 -
b00000000 .
b0000 /
b0001110000 0
#2000000
1!
1%
#4000000
0!
0%
#5000000
1"
1&
#6000000
1!
b0001110000 $
1%
b0001110000 (
b0001110000 )
b0011100000 *
b0001 +
b0001 /
b0011100000 0
#8000000
0!
0%
#10000000
1!
1%
b11111111 .
#12000000
0!
0%
#14000000
1!
b11111111 #
1%
b11111111 '
b11111111 ,
#16000000
0!
0%
#18000000
1!
b0011100000 $
1%
b0011100000 (
b0011100000 )
b0010100010 *
b0010 +
b0010 /
b0010100010 0
#20000000
0!
0%
#22000000
1!
1%
b00000000 .
#24000000
0!
0%
#26000000
1!
1%
#28000000
0!
0%
#30000000
1!
b0010100010 $
1%
b0010100010 (
b0010100010 )
b0100000100 *
b0011 +
b0011 /
b0100000100 0
#32000000
0!
0%
#34000000
1!
1%
b00000010 .
#36000000
0!
0%
#38000000
1!
1%
b00000010 -
#40000000
0!
0%
#42000000
1!
b0100000100 $
1%
b0100000100 (
b0100000100 )
b0100 +
b0100 /
#44000000
0!
0%
#46000000
1!
1%
#48000000
0!
0%
#50000000
1!
b00000001 #
1%
b00000001 '
b00000001 ,
#52000000
0!
0%
#54000000
1!
1%
b0100100100 *
b0101 +
b0101 /
b0100100100 0
#56000000
0!
0%
#58000000
1!
1%
#60000000
0!
0%
#62000000
1!
b00000011 #
1%
b00000011 '
b00000011 ,
#64000000
0!
0%
#66000000
1!
b0100100100 $
1%
b0100100100 (
b0100100100 )
b0101001100 *
b0110 +
b0110 /
b0101001100 0
#68000000
0!
0%
#70000000
1!
1%
#72000000
0!
0%
#74000000
1!
b00000001 #
1%
b00000001 '
b00000001 ,
#76000000
0!
0%
#78000000
1!
b0101001100 $
1%
b0101001100 (
b0101001100 )
b0101101100 *
b0111 +
b0111 /
b0101101100 0
#80000000
0!
0%
#82000000
1!
1%
b00000001 .
#84000000
0!
0%
#86000000
1!
b00000010 #
1%
b00000010 '
b00000010 ,
#88000000
0!
0%
#90000000
1!
b0101101100 $
1%
b0101101100 (
b0101101100 )
b0111101100 *
b1000 +
b1000 /
b0111101100 0
#92000000
0!
0%
#94000000
1!
1%
b00000010 .
#96000000
0!
0%
#98000000
1!
b00000001 #
1%
b00000001 '
b00000001 ,
#100000000
0!
0%
#102000000
1!
b0111101100 $
1%
b0111101100 (
b0111101100 )
b0101101100 *
b1001 +
b1001 /
b0101101100 0
#104000000
0!
0%
#106000000
1!
1%
b00000001 .
#108000000
0!
0%
#110000000
1!
b10000000 #
1%
b10000000 '
b10000000 ,
#112000000
0!
0%
#114000000
1!
b0101101100 $
1%
b0101101100 (
b0101101100 )
b0110011100 *
b1010 +
b1010 /
b0110011100 0
#116000000
0!
0%
#118000000
1!
1%
b10000000 .
#120000000
0!
0%
#122000000
1!
b01000000 #
1%
b01000000 '
b01000000 ,
#124000000
0!
0%
#126000000
1!
b0110011100 $
1%
b0110011100 (
b0110011100 )
b0110110101 *
b1011 +
b1011 /
b0110110101 0
#128000000
0!
0%
#130000000
1!
1%
b11111111 .
#132000000
0!
0%
#134000000
1!
b10111111 #
1%
b10111111 '
b10111111 ,
#136000000
0!
0%
#138000000
1!
b0110110101 $
1%
b0110110101 (
b0110110101 )
b0100010110 *
b1100 +
b1100 /
b0100010110 0
#140000000
0!
0%
#142000000
1!
1%
b00000001 .
#144000000
0!
0%
#146000000
1!
b00000001 #
1%
b00000001 '
b00000001 ,
#148000000
0!
0%
#150000000
1!
b0100010110 $
1%
b0100010110 (
b0100010110 )
b1111111111 *
b1101 +
b1101 /
b1111111111 0
#152000000
0!
0%
#154000000
1!
1%
b00000010 .
#156000000
0!
0%
#158000000
1!
b00000011 #
1%
b00000011 '
b00000011 ,
#160000000
0!
0%
#162000000
1!
b1111111111 $
1%
b1111111111 (
b1111111111 )
b1110 +
b1110 /
#164000000
0!
0%
#166000000
1!
1%
#168000000
0!
0%
#170000000
1!
1%
#172000000
0!
0%
#174000000
1!
1%
b1111 +
b1111 /
#176000000
0!
0%
#178000000
1!
1%
#180000000
0!
0%
#182000000
1!
1%
#184000000
0!
0%
#186000000
1!
1%
b0001110000 *
b0000 +
b0000 /
b0001110000 0
#188000000
0!
0%
#190000000
1!
1%
#192000000
0!
0%
#194000000
1!
1%
#196000000
0!
0%
#198000000
1!
b0001110000 $
1%
b0001110000 (
b0001110000 )
b0011100000 *
b0001 +
b0001 /
b0011100000 0
#200000000
0!
0%
#202000000
1!
1%
b11111111 .
#204000000
0!
0%
#206000000
1!
b11111111 #
1%
b11111111 '
b11111111 ,
#208000000
0!
0%
#210000000
1!
b0011100000 $
1%
b0011100000 (
b0011100000 )
b0010100010 *
b0010 +
b0010 /
b0010100010 0
#212000000
0!
0%
#214000000
1!
1%
b00000000 .
#216000000
0!
0%
#218000000
1!
1%
#220000000
0!
0%
#222000000
1!
b0010100010 $
1%
b0010100010 (
b0010100010 )
b0100000100 *
b0011 +
b0011 /
b0100000100 0
#224000000
0!
0%
#226000000
1!
1%
b00000010 .
#228000000
0!
0%
#230000000
1!
1%
#232000000
0!
0%
#234000000
1!
b0100000100 $
1%
b0100000100 (
b0100000100 )
b0100 +
b0100 /
#236000000
0!
0%
#238000000
1!
1%
#240000000
0!
0%
#242000000
1!
b00000001 #
1%
b00000001 '
b00000001 ,
#244000000
0!
0%
#246000000
1!
1%
b0100100100 *
b0101 +
b0101 /
b0100100100 0
#248000000
0!
0%
#250000000
1!
1%
#252000000
0!
0%
#254000000
1!
b00000011 #
1%
b00000011 '
b00000011 ,
#256000000
0!
0%
#258000000
1!
b0100100100 $
1%
b0100100100 (
b0100100100 )
b0101001100 *
b0110 +
b0110 /
b0101001100 0
#260000000
0!
0%
#262000000
1!
1%
#264000000
0!
0%
#266000000
1!
b00000001 #
1%
b00000001 '
b00000001 ,
#268000000
0!
0%
#270000000
1!
b0101001100 $
1%
b0101001100 (
b0101001100 )
b0101101100 *
b0111 +
b0111 /
b0101101100 0
#272000000
0!
0%
#274000000
1!
1%
b00000001 .
#276000000
0!
0%
#278000000
1!
b00000010 #
1%
b00000010 '
b00000010 ,
#280000000
0!
0%
#282000000
1!
b0101101100 $
1%
b0101101100 (
b0101101100 )
b0111101100 *
b1000 +
b1000 /
b0111101100 0
#284000000
0!
0%
#286000000
1!
1%
b00000010 .
#288000000
0!
0%
#290000000
1!
b00000001 #
1%
b00000001 '
b00000001 ,
#292000000
0!
0%
#294000000
1!
b0111101100 $
1%
b0111101100 (
b0111101100 )
b0101101100 *
b1001 +
b1001 /
b0101101100 0
#296000000
0!
0%
#298000000
1!
1%
b00000001 .
#300000000
0!
0%
#302000000
1!
b10000000 #
1%
b10000000 '
b10000000 ,
#304000000
0!
0%
#306000000
1!
b0101101100 $
1%
b0101101100 (
b0101101100 )
b0110011100 *
b1010 +
b1010 /
b0110011100 0
#308000000
0!
0%
#310000000
1!
1%
b10000000 .
#312000000
0!
0%
#314000000
1!
b01000000 #
1%
b01000000 '
b01000000 ,
#316000000
0!
0%
#318000000
1!
b0110011100 $
1%
b0110011100 (
b0110011100 )
b0110110101 *
b1011 +
b1011 /
b0110110101 0
#320000000
0!
0%
#322000000
1!
1%
b11111111 .
#324000000
0!
0%
#326000000
1!
b10111111 #
1%
b10111111 '
b10111111 ,
#328000000
0!
0%
#330000000
1!
b0110110101 $
1%
b0110110101 (
b0110110101 )
b0100010110 *
b1100 +
b1100 /
b0100010110 0
#332000000
0!
0%
#334000000
1!
1%
b00000001 .
#336000000
0!
0%
#338000000
1!
b00000001 #
1%
b00000001 '
b00000001 ,
#340000000
0!
0%
#342000000
1!
b0100010110 $
1%
b0100010110 (
b0100010110 )
b1111111111 *
b1101 +
b1101 /
b1111111111 0
#344000000
0!
0%
#346000000
1!
1%
b00000010 .
#348000000
0!
0%
#350000000
1!
b00000011 #
1%
b00000011 '
b00000011 ,
#352000000
0!
0%
#354000000
1!
b1111111111 $
1%
b1111111111 (
b1111111111 )
b1110 +
b1110 /
#356000000
0!
0%
#358000000
1!
1%
#360000000
0!
0%
#362000000
1!
1%
#364000000
0!
0%
#366000000
1!
1%
b1111 +
b1111 /
#368000000
0!
0%
#370000000
1!
1%
#372000000
0!
0%
#374000000
1!
1%
#376000000
0!
0%
#378000000
1!
1%
b0001110000 *
b0000 +
b0000 /
b0001110000 0
#380000000
0!
0%
#382000000
1!
1%
#384000000
0!
0%
#386000000
1!
1%
#388000000
0!
0%
#390000000
1!
b0001110000 $
1%
b0001110000 (
b0001110000 )
b0011100000 *
b0001 +
b0001 /
b0011100000 0
#392000000
0!
0%
#394000000
1!
1%
b11111111 .
#396000000
0!
0%
#398000000
1!
b11111111 #
1%
b11111111 '
b11111111 ,
#400000000
0!
0%
#402000000
1!
b0011100000 $
1%
b0011100000 (
b0011100000 )
b0010100010 *
b0010 +
b0010 /
b0010100010 0
#404000000
0!
0%
#406000000
1!
1%
b00000000 .
#408000000
0!
0%
#410000000
1!
1%
#412000000
0!
0%
#414000000
1!
b0010100010 $
1%
b0010100010 (
b0010100010 )
b0100000100 *
b0011 +
b0011 /
b0100000100 0
#416000000
0!
0%
#418000000
1!
1%
b00000010 .
#420000000
0!
0%
#422000000
1!
1%
#424000000
0!
0%
#426000000
1!
b0100000100 $
1%
b0100000100 (
b0100000100 )
b0100 +
b0100 /
#428000000
0!
0%
#430000000
1!
1%
#432000000
0!
0%
#434000000
1!
b00000001 #
1%
b00000001 '
b00000001 ,
#436000000
0!
0%
#438000000
1!
1%
b0100100100 *
b0101 +
b0101 /
b0100100100 0
#440000000
0!
0%
#442000000
1!
1%
#444000000
0!
0%
#446000000
1!
b00000011 #
1%
b00000011 '
b00000011 ,
#448000000
0!
0%
#450000000
1!
b0100100100 $
1%
b0100100100 (
b0100100100 )
b0101001100 *
b0110 +
b0110 /
b0101001100 0
#452000000
0!
0%
#454000000
1!
1%
#456000000
0!
0%
#458000000
1!
b00000001 #
1%
b00000001 '
b00000001 ,
#460000000
0!
0%
#462000000
1!
b0101001100 $
1%
b0101001100 (
b0101001100 )
b0101101100 *
b0111 +
b0111 /
b0101101100 0
#464000000
0!
0%
#466000000
1!
1%
b00000001 .
#468000000
0!
0%
#470000000
1!
b00000010 #
1%
b00000010 '
b00000010 ,
#472000000
0!
0%
#474000000
1!
b0101101100 $
1%
b0101101100 (
b0101101100 )
b0111101100 *
b1000 +
b1000 /
b0111101100 0
#476000000
0!
0%
#478000000
1!
1%
b00000010 .
#480000000
0!
0%
#482000000
1!
b00000001 #
1%
b00000001 '
b00000001 ,
#484000000
0!
0%
#486000000
1!
b0111101100 $
1%
b0111101100 (
b0111101100 )
b0101101100 *
b1001 +
b1001 /
b0101101100 0
#488000000
0!
0%
#490000000
1!
1%
b00000001 .
#492000000
0!
0%
#494000000
1!
b10000000 #
1%
b10000000 '
b10000000 ,
#496000000
0!
0%
#498000000
1!
b0101101100 $
1%
b0101101100 (
b0101101100 )
b0110011100 *
b1010 +
b1010 /
b0110011100 0
#500000000
0!
0%
#502000000
1!
1%
b10000000 .
#504000000
0!
0%
#506000000
1!
b01000000 #
1%
b01000000 '
b01000000 ,
#508000000
0!
0%
#510000000
1!
b0110011100 $
1%
b0110011100 (
b0110011100 )
b0110110101 *
b1011 +
b1011 /
b0110110101 0
#512000000
0!
0%
#514000000
1!
1%
b11111111 .
#516000000
0!
0%
#518000000
1!
b10111111 #
1%
b10111111 '
b10111111 ,
#520000000
0!
0%
#522000000
1!
b0110110101 $
1%
b0110110101 (
b0110110101 )
b0100010110 *
b1100 +
b1100 /
b0100010110 0
#524000000
0!
0%
#526000000
1!
1%
b00000001 .
#528000000
0!
0%
#530000000
1!
b00000001 #
1%
b00000001 '
b00000001 ,
#532000000
0!
0%
#534000000
1!
b0100010110 $
1%
b0100010110 (
b0100010110 )
b1111111111 *
b1101 +
b1101 /
b1111111111 0
#536000000
0!
0%
#538000000
1!
1%
b00000010 .
#540000000
0!
0%
#542000000
1!
b00000011 #
1%
b00000011 '
b00000011 ,
#544000000
0!
0%
#546000000
1!
b1111111111 $
1%
b1111111111 (
b1111111111 )
b1110 +
b1110 /
#548000000
0!
0%
#550000000
1!
1%
#552000000
0!
0%
#554000000
1!
1%
#556000000
0!
0%
#558000000
1!
1%
b1111 +
b1111 /
#560000000
0!
0%
#562000000
1!
1%
#564000000
0!
0%
#566000000
1!
1%
#568000000
0!
0%
#570000000
1!
1%
b0001110000 *
b0000 +
b0000 /
b0001110000 0
#572000000
0!
0%
#574000000
1!
1%
#576000000
0!
0%
#578000000
1!
1%
#580000000
0!
0%
#582000000
1!
b0001110000 $
1%
b0001110000 (
b0001110000 )
b0011100000 *
b0001 +
b0001 /
b0011100000 0
#584000000
0!
0%
#586000000
1!
1%
b11111111 .
#588000000
0!
0%
#590000000
1!
b11111111 #
1%
b11111111 '
b11111111 ,
#592000000
0!
0%
#594000000
1!
b0011100000 $
1%
b0011100000 (
b0011100000 )
b0010100010 *
b0010 +
b0010 /
b0010100010 0
#596000000
0!
0%
#598000000
1!
1%
b00000000 .
#600000000
0!
0%
#602000000
1!
1%
#604000000
0!
0%
#606000000
1!
b0010100010 $
1%
b0010100010 (
b0010100010 )
b0100000100 *
b0011 +
b0011 /
b0100000100 0
#608000000
0!
0%
#610000000
1!
1%
b00000010 .
#612000000
0!
0%
#614000000
1!
1%
#616000000
0!
0%
#618000000
1!
b0100000100 $
1%
b0100000100 (
b0100000100 )
b0100 +
b0100 /
#620000000
0!
0%
#622000000
1!
1%
#624000000
0!
0%
#626000000
1!
b00000001 #
1%
b00000001 '
b00000001 ,
#628000000
0!
0%
#630000000
1!
1%
b0100100100 *
b0101 +
b0101 /
b0100100100 0
#632000000
0!
0%
#634000000
1!
1%
#636000000
0!
0%
#638000000
1!
b00000011 #
1%
b00000011 '
b00000011 ,
#640000000
0!
0%
#642000000
1!
b0100100100 $
1%
b0100100100 (
b0100100100 )
b0101001100 *
b0110 +
b0110 /
b0101001100 0
#644000000
0!
0%
#646000000
1!
1%
#648000000
0!
0%
#650000000
1!
b00000001 #
1%
b00000001 '
b00000001 ,
#652000000
0!
0%
#654000000
1!
b0101001100 $
1%
b0101001100 (
b0101001100 )
b0101101100 *
b0111 +
b0111 /
b0101101100 0
#656000000
0!
0%
#658000000
1!
1%
b00000001 .
#660000000
0!
0%
#662000000
1!
b00000010 #
1%
b00000010 '
b00000010 ,
#664000000
0!
0%
#666000000
1!
b0101101100 $
1%
b0101101100 (
b0101101100 )
b0111101100 *
b1000 +
b1000 /
b0111101100 0
#668000000
0!
0%
#670000000
1!
1%
b00000010 .
#672000000
0!
0%
#674000000
1!
b00000001 #
1%
b00000001 '
b00000001 ,
#676000000
0!
0%
#678000000
1!
b0111101100 $
1%
b0111101100 (
b0111101100 )
b0101101100 *
b1001 +
b1001 /
b0101101100 0
#680000000
0!
0%
#682000000
1!
1%
b00000001 .
#684000000
0!
0%
#686000000
1!
b10000000 #
1%
b10000000 '
b10000000 ,
#688000000
0!
0%
#690000000
1!
b0101101100 $
1%
b0101101100 (
b0101101100 )
b0110011100 *
b1010 +
b1010 /
b0110011100 0
#692000000
0!
0%
#694000000
1!
1%
b10000000 .
#696000000
0!
0%
#698000000
1!
b01000000 #
1%
b01000000 '
b01000000 ,
#700000000
0!
0%
#702000000
1!
b0110011100 $
1%
b0110011100 (
b0110011100 )
b0110110101 *
b1011 +
b1011 /
b0110110101 0
#704000000
0!
0%
#706000000
1!
1%
b11111111 .
#708000000
0!
0%
#710000000
1!
b10111111 #
1%
b10111111 '
b10111111 ,
#712000000
0!
0%
#714000000
1!
b0110110101 $
1%
b0110110101 (
b0110110101 )
b0100010110 *
b1100 +
b1100 /
b0100010110 0
#716000000
0!
0%
#718000000
1!
1%
b00000001 .
#720000000
0!
0%
#722000000
1!
b00000001 #
1%
b00000001 '
b00000001 ,
#724000000
0!
0%
#726000000
1!
b0100010110 $
1%
b0100010110 (
b0100010110 )
b1111111111 *
b1101 +
b1101 /
b1111111111 0
#728000000
0!
0%
#730000000
1!
1%
b00000010 .
#732000000
0!
0%
#734000000
1!
b00000011 #
1%
b00000011 '
b00000011 ,
#736000000
0!
0%
#738000000
1!
b1111111111 $
1%
b1111111111 (
b1111111111 )
b1110 +
b1110 /
#740000000
0!
0%
#742000000
1!
1%
#744000000
0!
0%
#746000000
1!
1%
#748000000
0!
0%
#750000000
1!
1%
b1111 +
b1111 /
#752000000
0!
0%
#754000000
1!
1%
#756000000
0!
0%
#758000000
1!
1%
#760000000
0!
0%
#762000000
1!
1%
b0001110000 *
b0000 +
b0000 /
b0001110000 0
#764000000
0!
0%
#766000000
1!
1%
#768000000
0!
0%
#770000000
1!
1%
#772000000
0!
0%
#774000000
1!
b0001110000 $
1%
b0001110000 (
b0001110000 )
b0011100000 *
b0001 +
b0001 /
b0011100000 0
#776000000
0!
0%
#778000000
1!
1%
b11111111 .
#780000000
0!
0%
#782000000
1!
b11111111 #
1%
b11111111 '
b11111111 ,
#784000000
0!
0%
#786000000
1!
b0011100000 $
1%
b0011100000 (
b0011100000 )
b0010100010 *
b0010 +
b0010 /
b0010100010 0
#788000000
0!
0%
#790000000
1!
1%
b00000000 .
#792000000
0!
0%
#794000000
1!
1%
#796000000
0!
0%
#798000000
1!
b0010100010 $
1%
b0010100010 (
b0010100010 )
b0100000100 *
b0011 +
b0011 /
b0100000100 0
#800000000
0!
0%
#802000000
1!
1%
b00000010 .
#804000000
0!
0%
#806000000
1!
1%
#808000000
0!
0%
#810000000
1!
b0100000100 $
1%
b0100000100 (
b0100000100 )
b0100 +
b0100 /
#812000000
0!
0%
#814000000
1!
1%
