classProjectStuff/232/Project6/Project/hexdisplay.vhd
-- hexdisplay file

library ieee;
use ieee.std_logic_1164.all;
use ieee.numeric_std.all;

entity hexdisplay is

	port 
	(
		a	   : in UNSIGNED  (3 downto 0);
		result : out UNSIGNED (6 downto 0)
	);

end entity;

architecture rtl of hexdisplay is
begin

    -- 0 Means segment will be on, 1 means it will be off
    -- For some of these I am doing the inverse because it is a lot easier to type out

    -- Inverted bit 0
    result(0) <= '1' when a = "0001" or a = "0100" or a = "1011" or a = "1101" else '0'; 
    -- Inverted for bit 1
    result(1) <= '1' when a = "0101" or a = "0110" or a = "1011" or a = "1100" or a = "1110" or a = "1111" else '0';
    -- Inverted for bit 2
    result(2) <= '1' when a = "0010" or a = "1100" or a = "1110" or a = "1111" else '0';
    -- Inverted for bit 3
    result(3) <= '1' when a = "0001" or a = "0100" or a = "0111" or a = "1001" or a = "1010" or a = "1111" else '0';
    -- Inverted for bit 4
    result(4) <= '1' when a = "0001" or a = "0011" or a = "0100" or a = "0101" or a = "0111" or a = "1001" else '0';
    -- Inverted for bit 5
    result(5) <= '1' when a = "0001" or a = "0010" or a = "0011" or a = "0111" or a = "1101" else '0';
    -- Inverted for bit 6
    result(6) <= '1' when a = "0000" or a = "0001" or a = "0111" or a = "1100" else '0';


end rtl;

classProjectStuff/232/Project3/task1/timer.vhd
-- Quartus II VHDL Template
-- Four-State Moore State Machine

-- A Moore machine's outputs are dependent only on the current state.
-- The output is written only when the state changes.  (State
-- transitions are synchronous.)

library ieee;
use ieee.std_logic_1164.all;
use ieee.numeric_std.all;

entity timer is

	port(
		clk		 : in	std_logic;
		reset	 : in	std_logic;
        start	 : in	std_logic;
        react	 : in	std_logic;        
        redOut   : out std_logic;
        greenOut : out std_logic;
		mstime	 : out	std_logic_vector(7 downto 0)
	);

end entity;

architecture rtl of timer is

	-- Build an enumerated type for the state machine
	type state_type is (sIdle, sWait, sCount);

	-- Register to hold the current state
    signal state   : state_type;
    
    -- Counter for time for wait and count states
    signal count : unsigned(7 downto 0);

begin

	-- Logic to advance to the next state
	process (clk, reset)
	begin
		if reset = '0' then
            state <= sIdle;
            count <= (others => '0');
		elsif (rising_edge(clk)) then
			case state is
				when sIdle=>
					if start = '0' then
                        state <= sWait;
                    else
                        state <= sIdle;
					end if;
				when sWait=>
                    if count > "00000100" then -- State progresses and count resets
                        state <= sCount;
                        count <= (others => '0');
                    elsif react = '0' then -- If react button is hit early
                        state <= sIdle;
                        count <= (others => '1');
                    else -- State stays in wait and count increments
                        state <= sWait;
                        count <= count + 1; 
					end if;
				when sCount=>
					if react = '0' then -- Go to idle
						state <= sIdle;
                    else -- State stays the same and count increments
                        state <= sCount;
                        count <= count + 1; 
					end if;
			end case;
		end if;
	end process;

    greenOut <= '1' when state = sCount else '0';
    redOut   <= '1' when state = sWait else '0';
    mstime   <= "00000000" when state = sWait else std_logic_vector(count(7 downto 0));

        
end rtl;

classProjectStuff/232/Project3/task1/timingtest.vhd
-- Bruce A. Maxwell
-- Spring 2013
-- CS 232 Lab 3
-- Test bench for the bright state machine circuit
--

library ieee;
use ieee.std_logic_1164.all;
use ieee.numeric_std.all;

-- a test bench has no inputs or outputs
entity timingtest is
end timingtest;

-- architecture
architecture test of timingtest is

  -- internal signals for everything we want to send to or receive from the
  -- test circuit
  signal reset, start, react: std_logic;
  signal rled: std_logic;
  signal gled: std_logic;
  signal timeval: std_logic_vector(7 downto 0);
  signal disp0 : unsigned(6 downto 0);
  signal disp1 : unsigned(6 downto 0);
  signal disptime0 : unsigned(3 downto 0);
  signal disptime1 : unsigned(3 downto 0);

  component timer
    port(
		clk		 : in	std_logic;
		reset	 : in	std_logic;
        start	 : in	std_logic;
        react	 : in	std_logic;        
        redOut   : out std_logic;
        greenOut : out std_logic;
		mstime	 : out	std_logic_vector(7 downto 0)
      );
  end component;

  component hexdisplay
    port(
        A: in UNSIGNED(3 downto 0);
        result: out UNSIGNED(6 downto 0)
        );
  end component;

  -- signals for making the clock
  constant num_cycles : integer := 20;
  signal clk : std_logic := '1';

begin
    -- we can use a process and a for loop to generate a clock signal
    process begin
      for i in 1 to num_cycles loop
        clk <= not clk;
        wait for 5 ns;
        clk <= not clk;
        wait for 5 ns;
      end loop;
      wait;
    end process;

  -- these are timed signal assignments to create specific patterns
  reset <= '0', '1' after 8 ns, '0' after 100 ns, '1' after 200 ns;
  start <= '1', '0' after 12 ns, '1' after 22 ns; 
  react <= '1', '0' after 150 ns, '1' after 165 ns;

  disptime0 <= unsigned(timeval(3 downto 0));
  disptime1 <= unsigned(timeval(7 downto 4));


  -- this instantiates a bright circuit and sets up the inputs and outputs
  B0: timer port map (clk, reset, start, react, rled, gled, timeval);
  B1: hexdisplay port map(disptime0, disp0);
  B2: hexdisplay port map(disptime1, disp1);

end test;

classProjectStuff/232/Project3/task1/timingtest.vcd
$date
  Sun Sep 27 12:45:14 2020
$end
$version
  GHDL v0
$end
$timescale
  1 fs
$end
$scope module standard $end
$upscope $end
$scope module std_logic_1164 $end
$upscope $end
$scope module numeric_std $end
$upscope $end
$scope module timingtest $end
$var reg 1 ! reset $end
$var reg 1 " start $end
$var reg 1 # react $end
$var reg 1 $ rled $end
$var reg 1 % gled $end
$var reg 8 & timeval[7:0] $end
$var reg 7 ' disp0[6:0] $end
$var reg 7 ( disp1[6:0] $end
$var reg 4 ) disptime0[3:0] $end
$var reg 4 * disptime1[3:0] $end
$var reg 1 + clk $end
$scope module b0 $end
$var reg 1 , clk $end
$var reg 1 - reset $end
$var reg 1 . start $end
$var reg 1 / react $end
$var reg 1 0 redout $end
$var reg 1 1 greenout $end
$var reg 8 2 mstime[7:0] $end
$comment state is not handled $end
$var reg 8 3 count[7:0] $end
$upscope $end
$scope module b1 $end
$var reg 4 4 a[3:0] $end
$var reg 7 5 result[6:0] $end
$upscope $end
$scope module b2 $end
$var reg 4 6 a[3:0] $end
$var reg 7 7 result[6:0] $end
$upscope $end
$upscope $end
$enddefinitions $end
#0
0!
1"
1#
0$
0%
b00000000 &
b1000000 '
b1000000 (
b0000 )
b0000 *
0+
0,
0-
1.
1/
00
01
b00000000 2
b00000000 3
b0000 4
b1000000 5
b0000 6
b1000000 7
#5000000
1+
1,
#8000000
1!
1-
#10000000
0+
0,
#12000000
0"
0.
#15000000
1$
1+
1,
10
#20000000
0+
0,
#22000000
1"
1.
#25000000
1+
1,
b00000001 3
#30000000
0+
0,
#35000000
1+
1,
b00000010 3
#40000000
0#
0+
0,
0/
#45000000
0$
b11111111 &
b0001110 '
b0001110 (
b1111 )
b1111 *
1+
1,
00
b11111111 2
b11111111 3
b1111 4
b0001110 5
b1111 6
b0001110 7
#50000000
0+
0,
#55000000
1#
1+
1,
1/
#60000000
0+
0,
#65000000
1+
1,
#70000000
0+
0,
#75000000
1+
1,
#80000000
0+
0,
#85000000
1+
1,
#90000000
0+
0,
#95000000
1+
1,
#100000000
0!
b00000000 &
b1000000 '
b1000000 (
b0000 )
b0000 *
0+
0,
0-
b00000000 2
b00000000 3
b0000 4
b1000000 5
b0000 6
b1000000 7
#105000000
1+
1,
#110000000
0+
0,
#115000000
1!
1+
1,
1-
