classProjectStuff/232/Project8/alu.vhd
-- Owen Goldthwaite
-- CS 232 Spring 2020
library ieee;
use ieee.std_logic_1164.all;
use ieee.numeric_std.all;

-- The alu circuit implements the specified operation on alu_srcA and alu_srcB, putting
-- the result in dest and setting the appropriate condition flags.

-- The opcode meanings are shown in the case statement below

-- condition outputs
-- cr(0) <= '1' if the result of the operation is 0
-- cr(1) <= '1' if there is a 2's complement overflow
-- cr(2) <= '1' if the result of the operation is negative
-- cr(3) <= '1' if the operation generated a carry of '1'

-- Note that the and/or/xor operations are defined on std_logic_vectors, so you
-- may have to convert the alu_srcA and alu_srcB signals to std_logic_vectors, execute
-- the operation, and then convert the result back to an unsigned.  You can do
-- this all within a single expression.


entity alu is
  
  port (
    alu_srcA : in  unsigned(15 downto 0);         -- input A
    alu_srcB : in  unsigned(15 downto 0);         -- input B
    op   : in  std_logic_vector(2 downto 0);  -- operation
    cr   : out std_logic_vector(3 downto 0);  -- condition outputs
    dest : out unsigned(15 downto 0));        -- output value

end alu;

architecture test of alu is

  -- The signal tdest is an intermediate signal to hold the result and
  -- catch the carry bit in location 16.
  signal tdest : unsigned(16 downto 0);  
  
  -- Note that you should always put the carry bit into index 16, even if the
  -- carry is shifted out the right side of the number (into position -1) in
  -- the case of a shift or rotate operation.  This makes it easy to set the
  -- condition flag in the case of a carry out.

begin  -- test
  process (alu_srcA, alu_srcB, op)
  begin  -- process
    case op is
      when "000" =>        -- addition     tdest = alu_srcA + alu_srcB
        tdest <= ('0' & alu_srcA) + ('0' & alu_srcB);
      when "001" =>        -- subtraction  tdest = alu_srcA - alu_srcB
        tdest <= ('0' & alu_srcA) - ('0' & alu_srcB);
      when "010" =>        -- and          tdest = alu_srcA and alu_srcB
        tdest(15 downto 0) <= unsigned(std_logic_vector(alu_srcA) and std_logic_vector(alu_srcB));
        tdest(16) <= '0';
      when "011" =>        -- or           tdest = alu_srcA or alu_srcB
        tdest(15 downto 0) <= unsigned(std_logic_vector(alu_srcA) or std_logic_vector(alu_srcB));
        tdest(16) <= '0';
      when "100" =>        -- xor          tdest = alu_srcA xor alu_srcB
        tdest(15 downto 0) <= unsigned(std_logic_vector(alu_srcA) xor std_logic_vector(alu_srcB));
        tdest(16) <= '0';
      when "101" =>        -- shift        tdest = alu_srcA shifted left arithmetic by one if alu_srcB(0) is 0, otherwise right
        if(alu_srcB(0) = '0') then
            tdest(15 downto 0) <= unsigned(shift_left(signed(alu_srcA),1));

            if(alu_srcA(15) = '1') then -- Checking for carry
                tdest(16) <= '1';
            else
                tdest(16) <= '0';
            end if;
        else
            tdest(15 downto 0) <= unsigned(shift_right(signed(alu_srcA),1));

            if(alu_srcA(0) = '1') then -- Checking for carry
                tdest(16) <= '1';
            else
                tdest(16) <= '0';
            end if;
        end if;
      when "110" =>        -- rotate       tdest = alu_srcA rotated left by one if alu_srcB(0) is 0, otherwise right
        if(alu_srcB(0) = '0') then
          tdest(15 downto 0) <= rotate_left(alu_srcA,1);

            if(alu_srcA(15) = '1') then -- Checking for carry
                tdest(16) <= '1';
            else
                tdest(16) <= '0';
            end if;
        else
          tdest(15 downto 0) <= rotate_right(alu_srcA,1);

            if(alu_srcA(0) = '1') then -- Checking for carry
                tdest(16) <= '1';
            else
                tdest(16) <= '0';
            end if;
        end if;
      when "111" =>        -- pass         tdest = alu_srcA
        tdest(15 downto 0) <= alu_srcA;
      when others =>
        null;
    end case;
  end process;

  -- connect the low 16 bits of tdest to dest here
  dest <= tdest(15 downto 0);

  -- If result is 0
  cr(0) <= '1' when tdest(15 downto 0) = "0000000000000000" else '0';

  -- Addition and subtraction overflow
  cr(1) <= '1' when (op = "000" and (alu_srcA(15) = alu_srcB(15)) and (alu_srcA(15) /= tdest(15))) or 
                  ( op = "001" and alu_srcA(15) = '1' and alu_srcB(15) = '0' and tdest(15) = '0' ) or
                  ( op = "001" and alu_srcA(15) = '0' and alu_srcB(15) = '1' and tdest(15) = '1' ) else '0';

  -- If result is negative
  cr(2) <= '1' when tdest(15) = '1' else '0';

  -- If there is a carry
  cr(3) <= '1' when tdest(16) = '1' else '0';
    

end test;

classProjectStuff/232/Project7/alutestbench.vhd
library ieee;
use ieee.std_logic_1164.all;
use ieee.numeric_std.all;

entity alutestbench is
end alutestbench;

architecture test of alutestbench is
  constant num_cycles : integer := 20;

  
  signal state: unsigned(3 downto 0);
  signal alu_srcA: unsigned(15 downto 0);
  signal alu_srcB: unsigned(15 downto 0);
  signal dest: unsigned(15 downto 0) := "0000000000000000";
  signal opcode: std_logic_vector(2 downto 0);

  signal output: std_logic_vector(15 downto 0) := "0000000000000000";
  signal CR: std_logic_vector(3 downto 0) := "0000";
  signal clk: std_logic := '1';
  signal reset: std_logic;
  
  -- component statement for the ALU
  component alu
    port (
      alu_srcA : in  unsigned(15 downto 0);         -- input A
      alu_srcB : in  unsigned(15 downto 0);         -- input B
      op   : in  std_logic_vector(2 downto 0);  -- operation
      cr   : out std_logic_vector(3 downto 0);  -- condition outputs
      dest : out unsigned(15 downto 0));        -- output value
  end component;
  
begin

  -- start off with a short reset
  reset <= '0', '1' after 1 ns;

  -- create a clock
  process
  begin
    for i in 1 to num_cycles loop
      clk <= not clk;
      wait for 1 ns;
      clk <= not clk;
      wait for 1 ns;
    end loop;
    wait;
  end process;
  
  output <= std_logic_vector(dest); -- connect dest and the output

  process(clk, reset)
  begin 
    if reset = '0' then
      alu_srcA <= "0000000000000000";
      alu_srcB <= "0000000000000000";
      state <= "0000";
    elsif rising_edge(clk) then
      case state is
        when "0000" =>
          alu_srcA <= x"7FFF";
          alu_srcB <= x"0002";
          opcode <= "000"; -- addition, answer should be x8001, flags "0110"
          state <= state + 1;
        when "0001" =>
          alu_srcA <= x"FF10";
          alu_srcB <= x"FFFF";
          opcode <= "000"; -- addition, answer should be xFF0F, flags "1100"
          state <= state + 1;
        when "0010" =>
          alu_srcA <= x"0014";
          alu_srcB <= x"0012";
          opcode <= "001"; -- subtraction, answer should be x0002, flags "0000"
          state <= state + 1;
        when "0011" =>
          alu_srcA <= x"FFFE";
          alu_srcB <= x"FFFF";
          opcode <= "001"; -- subtraction, answer should be xFFFF, flags "1100"
          state <= state + 1;
        when "0100" =>
          alu_srcA <= x"FFFF";
          alu_srcB <= x"AAAA";
          opcode <= "010"; -- and, answer should be xAAAA, flags "0100"
          state <= state + 1;
        when "0101" =>
          alu_srcA <= x"00FF";
          alu_srcB <= x"AAAA"; -- and, answer should be x00AA, flags "0000"
          opcode <= "010";
          state <= state + 1;
        when "0110" =>
          alu_srcA <= x"FFFF";
          alu_srcB <= x"AAAA";
          opcode <= "011"; -- or, answer should be xFFFF, flags "0100"
          state <= state + 1;
        when "0111" =>
          alu_srcA <= x"FF00";
          alu_srcB <= x"AAAA"; -- or, answer should be xFFAA, flags "0100"
          opcode <= "011";
          state <= state + 1;
        when "1000" =>
          alu_srcA <= x"FFFF";
          alu_srcB <= x"AAAA";
          opcode <= "100"; -- xor, answer should be x5555, flags "0000"
          state <= state + 1;
        when "1001" =>
          alu_srcA <= x"FF00";
          alu_srcB <= x"AAAA";
          opcode <= "100"; -- xor, answer should be x55AA, flags "0000"
          state <= state + 1;
        when "1010" =>
          alu_srcA <= x"AAAA";
          alu_srcB <= x"0000";
          opcode <= "101"; -- shift, left by 1, answer should be x5554, flags "1000"
          state <= state + 1;
        when "1011" =>
          alu_srcA <= x"AAAA";
          alu_srcB <= x"0001";
          opcode <= "101"; -- shift, right by 1, answer should be xD555, flags "0100"
          state <= state + 1;
        when "1100" =>
          alu_srcA <= x"AAAA";
          alu_srcB <= x"0000";
          opcode <= "110"; -- rotate, left by 1, answer should be x5555, flags "1000"
          state <= state + 1;
        when "1101" =>
          alu_srcA <= x"AAAA";
          alu_srcB <= x"0001";
          opcode <= "110"; -- rotate, right by 1, answer should be x5555, flags "0000"
          state <= state + 1;
        when "1110" =>
          alu_srcA <= x"0000";
          alu_srcB <= x"0234";
          opcode <= "111"; -- pass through, answer should be x0000, flags "0001"
          state <= state + 1;
        when others =>
          alu_srcA <= x"F012";
          alu_srcB <= x"0000";
          opcode <= "111"; -- pass through, answer should be xF012, flags "0100"
          state <= state + 1;
      end case;
    end if;
  end process;


  aluinstance: alu
  port map( alu_srcA => alu_srcA, alu_srcB => alu_srcB, dest => dest, op => opcode, cr => CR );

end test;

classProjectStuff/232/Project8/alutestbench.vcd
$date
  Sun Nov 22 11:22:14 2020
$end
$version
  GHDL v0
$end
$timescale
  1 fs
$end
$scope module standard $end
$upscope $end
$scope module std_logic_1164 $end
$upscope $end
$scope module numeric_std $end
$upscope $end
$scope module alutestbench $end
$var reg 4 ! state[3:0] $end
$var reg 16 " alu_srca[15:0] $end
$var reg 16 # alu_srcb[15:0] $end
$var reg 16 $ dest[15:0] $end
$var reg 3 % opcode[2:0] $end
$var reg 16 & output[15:0] $end
$var reg 4 ' cr[3:0] $end
$var reg 1 ( clk $end
$var reg 1 ) reset $end
$scope module aluinstance $end
$var reg 16 * alu_srca[15:0] $end
$var reg 16 + alu_srcb[15:0] $end
$var reg 3 , op[2:0] $end
$var reg 4 - cr[3:0] $end
$var reg 16 . dest[15:0] $end
$var reg 17 / tdest[16:0] $end
$upscope $end
$upscope $end
$enddefinitions $end
#0
b0000 !
b0000000000000000 "
b0000000000000000 #
bUUUUUUUUUUUUUUUU $
bUUU %
bUUUUUUUUUUUUUUUU &
b1111 '
0(
0)
b0000000000000000 *
b0000000000000000 +
bUUU ,
b1111 -
bUUUUUUUUUUUUUUUU .
bUUUUUUUUUUUUUUUUU /
#1000000
b0001 !
b0111111111111111 "
b0000000000000010 #
b1000000000000001 $
b000 %
b1000000000000001 &
1(
1)
b0111111111111111 *
b0000000000000010 +
b000 ,
b1000000000000001 .
b01000000000000001 /
#2000000
0(
#3000000
b0010 !
b1111111100010000 "
b1111111111111111 #
b1111111100001111 $
b1111111100001111 &
1(
b1111111100010000 *
b1111111111111111 +
b1111111100001111 .
b11111111100001111 /
#4000000
0(
#5000000
b0011 !
b0000000000010100 "
b0000000000010010 #
b0000000000000010 $
b001 %
b0000000000000010 &
1(
b0000000000010100 *
b0000000000010010 +
b001 ,
b0000000000000010 .
b00000000000000010 /
#6000000
0(
#7000000
b0100 !
b1111111111111110 "
b1111111111111111 #
b1111111111111111 $
b1111111111111111 &
1(
b1111111111111110 *
b1111111111111111 +
b1111111111111111 .
b11111111111111111 /
#8000000
0(
#9000000
b0101 !
b1111111111111111 "
b1010101010101010 #
b1010101010101010 $
b010 %
b1010101010101010 &
1(
b1111111111111111 *
b1010101010101010 +
b010 ,
b1010101010101010 .
b01010101010101010 /
#10000000
0(
#11000000
b0110 !
b0000000011111111 "
b0000000010101010 $
b0000000010101010 &
1(
b0000000011111111 *
b0000000010101010 .
b00000000010101010 /
#12000000
0(
#13000000
b0111 !
b1111111111111111 "
b1111111111111111 $
b011 %
b1111111111111111 &
1(
b1111111111111111 *
b011 ,
b1111111111111111 .
b01111111111111111 /
#14000000
0(
#15000000
b1000 !
b1111111100000000 "
b1111111110101010 $
b1111111110101010 &
1(
b1111111100000000 *
b1111111110101010 .
b01111111110101010 /
#16000000
0(
#17000000
b1001 !
b1111111111111111 "
b0101010101010101 $
b100 %
b0101010101010101 &
1(
b1111111111111111 *
b100 ,
b0101010101010101 .
b00101010101010101 /
#18000000
0(
#19000000
b1010 !
b1111111100000000 "
b0101010110101010 $
b0101010110101010 &
1(
b1111111100000000 *
b0101010110101010 .
b00101010110101010 /
#20000000
0(
#21000000
b1011 !
b1010101010101010 "
b0000000000000000 #
b0101010101010100 $
b101 %
b0101010101010100 &
1(
b1010101010101010 *
b0000000000000000 +
b101 ,
b0101010101010100 .
b10101010101010100 /
#22000000
0(
#23000000
b1100 !
b0000000000000001 #
b1101010101010101 $
b1101010101010101 &
1(
b0000000000000001 +
b1101010101010101 .
b01101010101010101 /
#24000000
0(
#25000000
b1101 !
b0000000000000000 #
b0101010101010101 $
b110 %
b0101010101010101 &
1(
b0000000000000000 +
b110 ,
b0101010101010101 .
b10101010101010101 /
#26000000
0(
#27000000
b1110 !
b0000000000000001 #
1(
b0000000000000001 +
b00101010101010101 /
#28000000
0(
#29000000
b1111 !
b0000000000000000 "
b0000001000110100 #
b0000000000000000 $
b111 %
b0000000000000000 &
1(
b0000000000000000 *
b0000001000110100 +
b111 ,
b0000000000000000 .
b00000000000000000 /
#30000000
0(
#31000000
b0000 !
b1111000000010010 "
b0000000000000000 #
b1111000000010010 $
b1111000000010010 &
1(
b1111000000010010 *
b0000000000000000 +
b1111000000010010 .
b01111000000010010 /
#32000000
0(
#33000000
b0001 !
b0111111111111111 "
b0000000000000010 #
b1000000000000001 $
b000 %
b1000000000000001 &
1(
b0111111111111111 *
b0000000000000010 +
b000 ,
b1000000000000001 .
b01000000000000001 /
#34000000
0(
#35000000
b0010 !
b1111111100010000 "
b1111111111111111 #
b1111111100001111 $
b1111111100001111 &
1(
b1111111100010000 *
b1111111111111111 +
b1111111100001111 .
b11111111100001111 /
#36000000
0(
#37000000
b0011 !
b0000000000010100 "
b0000000000010010 #
b0000000000000010 $
b001 %
b0000000000000010 &
1(
b0000000000010100 *
b0000000000010010 +
b001 ,
b0000000000000010 .
b00000000000000010 /
#38000000
0(
#39000000
b0100 !
b1111111111111110 "
b1111111111111111 #
b1111111111111111 $
b1111111111111111 &
1(
b1111111111111110 *
b1111111111111111 +
b1111111111111111 .
b11111111111111111 /
