classProjectStuff/232/Project6/Project/hexdisplay.vhd
-- hexdisplay file

library ieee;
use ieee.std_logic_1164.all;
use ieee.numeric_std.all;

entity hexdisplay is

	port 
	(
		a	   : in UNSIGNED  (3 downto 0);
		result : out UNSIGNED (6 downto 0)
	);

end entity;

architecture rtl of hexdisplay is
begin

    -- 0 Means segment will be on, 1 means it will be off
    -- For some of these I am doing the inverse because it is a lot easier to type out

    -- Inverted bit 0
    result(0) <= '1' when a = "0001" or a = "0100" or a = "1011" or a = "1101" else '0'; 
    -- Inverted for bit 1
    result(1) <= '1' when a = "0101" or a = "0110" or a = "1011" or a = "1100" or a = "1110" or a = "1111" else '0';
    -- Inverted for bit 2
    result(2) <= '1' when a = "0010" or a = "1100" or a = "1110" or a = "1111" else '0';
    -- Inverted for bit 3
    result(3) <= '1' when a = "0001" or a = "0100" or a = "0111" or a = "1001" or a = "1010" or a = "1111" else '0';
    -- Inverted for bit 4
    result(4) <= '1' when a = "0001" or a = "0011" or a = "0100" or a = "0101" or a = "0111" or a = "1001" else '0';
    -- Inverted for bit 5
    result(5) <= '1' when a = "0001" or a = "0010" or a = "0011" or a = "0111" or a = "1101" else '0';
    -- Inverted for bit 6
    result(6) <= '1' when a = "0000" or a = "0001" or a = "0111" or a = "1100" else '0';


end rtl;

classProjectStuff/232/Project2/task1/hextest.vhd
-- Bruce Maxwell
-- Spring 2015
-- CS 232 Project 2
--

library ieee;
use ieee.std_logic_1164.all;
use ieee.numeric_std.all;


entity hextest is
end entity;

architecture test of hextest is
  signal A: UNSIGNED(3 downto 0);
  signal Aout: UNSIGNED(6 downto 0);

  component hexdisplay
  port(
  A: in UNSIGNED(3 downto 0);
  result: out UNSIGNED(6 downto 0)
  );
  end component;
    
  begin

    A(3) <= '0', '1' after 200 ns, '0' after 400 ns;
    A(2) <= '0', '1' after 100 ns, '0' after 200 ns, '1' after 300 ns;
    A(1) <= '0', '1' after 50 ns, '0' after 100 ns, '1' after 150 ns, '0' after 200 ns, '1' after 250 ns, '0' after 300 ns, '1' after 350 ns;
    A(0) <= '0', '1' after 25 ns, '0' after 50 ns, '1' after 75 ns, '0' after 100 ns, '1' after 125 ns, '0' after 150 ns, '1' after 175 ns, '0' after 200 ns, '1' after 225 ns, '0' after 250 ns, '1' after 275 ns, '0' after 300 ns , '1' after 325 ns, '0' after 350 ns, '1' after 375 ns;

    C0: hexdisplay port map( A, Aout );

  end test;

classProjectStuff/232/Project2/task1/hextest.vcd
$date
  Sun Sep 20 11:03:49 2020
$end
$version
  GHDL v0
$end
$timescale
  1 fs
$end
$scope module standard $end
$upscope $end
$scope module std_logic_1164 $end
$upscope $end
$scope module numeric_std $end
$upscope $end
$scope module hextest $end
$var reg 4 ! a[3:0] $end
$var reg 7 " aout[6:0] $end
$scope module c0 $end
$var reg 4 # a[3:0] $end
$var reg 7 $ result[6:0] $end
$upscope $end
$upscope $end
$enddefinitions $end
#0
b0000 !
b1000000 "
b0000 #
b1000000 $
#25000000
b0001 !
b1111001 "
b0001 #
b1111001 $
#50000000
b0010 !
b0100100 "
b0010 #
b0100100 $
#75000000
b0011 !
b0110000 "
b0011 #
b0110000 $
#100000000
b0100 !
b0011001 "
b0100 #
b0011001 $
#125000000
b0101 !
b0010010 "
b0101 #
b0010010 $
#150000000
b0110 !
b0000010 "
b0110 #
b0000010 $
#175000000
b0111 !
b1111000 "
b0111 #
b1111000 $
#200000000
b1000 !
b0000000 "
b1000 #
b0000000 $
#225000000
b1001 !
b0011000 "
b1001 #
b0011000 $
#250000000
b1010 !
b0001000 "
b1010 #
b0001000 $
#275000000
b1011 !
b0000011 "
b1011 #
b0000011 $
#300000000
b1100 !
b1000110 "
b1100 #
b1000110 $
#325000000
b1101 !
b0100001 "
b1101 #
b0100001 $
#350000000
b1110 !
b0000110 "
b1110 #
b0000110 $
#375000000
b1111 !
b0001110 "
b1111 #
b0001110 $
#400000000
b0111 !
b1111000 "
b0111 #
b1111000 $
