classProjectStuff/232/Project3/Lab3/bright.vhd
-- Quartus II VHDL Template
-- Four-State Moore State Machine

-- A Moore machine's outputs are dependent only on the current state.
-- The output is written only when the state changes.  (State
-- transitions are synchronous.)

library ieee;
use ieee.std_logic_1164.all;
use ieee.numeric_std.all;

entity bright is

	port(
		clk		 : in	std_logic;
        reset	 : in	std_logic;
        buttonOne : in std_logic;
        buttonTwo : in std_logic;
        buttonThree : in std_logic;
        redOutput : out std_logic_vector(2 downto 0);
        greenOutput : out std_logic
	);

end entity;

architecture rtl of bright is

	-- Build an enumerated type for the state machine
	type state_type is (s0, s1, s2, s3);

	-- Register to hold the current state
	signal state   : state_type;

begin

	-- Logic to advance to the next state
	process (clk, reset)
	begin
		if reset = '0' then
			state <= s0;
		elsif (rising_edge(clk)) then
			case state is
				when s0=>
					if buttonOne = '0' then
						state <= s1;
					else
						state <= s0;
					end if;
				when s1=>
					if buttonTwo = '0' then
						state <= s2;
					elsif buttonThree = '0' then
                        state <= s0;
                    else
						state <= s1;
					end if;
				when s2=>
					if buttonThree = '0' then
						state <= s3;
					elsif buttonOne = '0' then
                        state <= s0;
                    else
                        state <= s2;
					end if;
				when s3 =>
					if buttonOne = '0' or buttonTwo = '0' then
						state <= s0;
					else
						state <= s3;
					end if;
			end case;
		end if;
	end process;

	-- Output depends solely on the current state
	process (state)
	begin
		case state is
			when s0 =>
                redOutput(0) <= '1';
				redOutput(1) <= '0';
				redOutput(2) <= '0';
				greenOutput <= '0';                
			when s1 =>
                redOutput(0) <= '0';
                redOutput(1) <= '1';
                redOutput(2) <= '0';
                greenOutput <= '0'; 
			when s2 =>
                redOutput(0) <= '0';
                redOutput(1) <= '0';
                redOutput(2) <= '1';
                greenOutput <= '0'; 
			when s3 =>
                redOutput(0) <= '0';
                redOutput(1) <= '0';
                redOutput(2) <= '0';
                greenOutput <= '1'; 
		end case;
	end process;

end rtl;

classProjectStuff/232/Project3/Lab3/brighttest.vhd
-- Bruce A. Maxwell
-- Spring 2013
-- CS 232 Lab 3
-- Test bench for the bright state machine circuit
--

library ieee;
use ieee.std_logic_1164.all;

-- a test bench has no inputs or outputs
entity brighttest is
end brighttest;

-- architecture
architecture test of brighttest is

  -- internal signals for everything we want to send to or receive from the
  -- test circuit
  signal Reset, P1, P2, P3: std_logic;
  signal rled: std_logic_vector (2 downto 0);
  signal gled: std_logic;

  -- the component statement lets us instantiate a bright circuit
  component bright
    port(
      clk		 : in	std_logic;
      buttonOne	 : in	std_logic;
      buttonTwo	: in std_logic;
      buttonThree	: in std_logic;
      reset	 : in	std_logic;
      redOutput	 : out	std_logic_vector(2 downto 0);
      greenOutput : out std_logic
      );
  end component;

  -- signals for making the clock
  constant num_cycles : integer := 20;
  signal clk : std_logic := '1';

begin

  -- these are timed signal assignments to create specific patterns
  Reset <= '0', '1' after 7 ns;
  P1 <= '1', '0' after 20 ns, '1' after 35 ns, '0' after 105 ns, '1' after 125 ns,
      '0' after 155 ns, '1' after 165 ns;
  P2 <= '1', '0' after 45 ns, '1' after 65 ns, '0' after 135 ns, '1' after 145 ns;
  P3 <= '1', '0' after 75 ns, '1' after 90 ns;
  

  -- we can use a process and a for loop to generate a clock signal
  process begin
    for i in 1 to num_cycles loop
      clk <= not clk;
      wait for 5 ns;
      clk <= not clk;
      wait for 5 ns;
    end loop;
    wait;
  end process;

  -- this instantiates a bright circuit and sets up the inputs and outputs
  B0: bright port map (clk, P1, P2, P3, reset, rled, gled);
end test;

classProjectStuff/232/Project3/Lab3/brighttest.vcd
$date
  Sun Sep 27 11:07:46 2020
$end
$version
  GHDL v0
$end
$timescale
  1 fs
$end
$scope module standard $end
$upscope $end
$scope module std_logic_1164 $end
$upscope $end
$scope module numeric_std $end
$upscope $end
$scope module brighttest $end
$var reg 1 ! reset $end
$var reg 1 " p1 $end
$var reg 1 # p2 $end
$var reg 1 $ p3 $end
$var reg 3 % rled[2:0] $end
$var reg 1 & gled $end
$var reg 1 ' clk $end
$scope module b0 $end
$var reg 1 ( clk $end
$var reg 1 ) reset $end
$var reg 1 * buttonone $end
$var reg 1 + buttontwo $end
$var reg 1 , buttonthree $end
$var reg 3 - redoutput[2:0] $end
$var reg 1 . greenoutput $end
$comment state is not handled $end
$upscope $end
$upscope $end
$enddefinitions $end
#0
0!
1"
1#
1$
b001 %
0&
0'
0(
0)
1*
1+
1,
b001 -
0.
#5000000
1'
1(
#7000000
1!
1)
#10000000
0'
0(
#15000000
1'
1(
#20000000
0"
0'
0(
0*
#25000000
b010 %
1'
1(
b010 -
#30000000
0'
0(
#35000000
1"
1'
1(
1*
#40000000
0'
0(
#45000000
0#
b100 %
1'
1(
0+
b100 -
#50000000
0'
0(
#55000000
1'
1(
#60000000
0'
0(
#65000000
1#
1'
1(
1+
#70000000
0'
0(
#75000000
0$
b000 %
1&
1'
1(
0,
b000 -
1.
#80000000
0'
0(
#85000000
1'
1(
#90000000
1$
0'
0(
1,
#95000000
1'
1(
#100000000
0'
0(
#105000000
0"
b001 %
0&
1'
1(
0*
b001 -
0.
#110000000
0'
0(
#115000000
b010 %
1'
1(
b010 -
#120000000
0'
0(
#125000000
1"
1'
1(
1*
#130000000
0'
0(
#135000000
0#
b100 %
1'
1(
0+
b100 -
#140000000
0'
0(
#145000000
1#
1'
1(
1+
#150000000
0'
0(
#155000000
0"
b001 %
1'
1(
0*
b001 -
#160000000
0'
0(
#165000000
1"
1'
1(
1*
