classProjectStuff/232/Project4/task1/lightrom.vhd
-- Owen Goldthwaite
-- CS232

library ieee;
use ieee.std_logic_1164.all;
use ieee.numeric_std.all;

entity lightrom is
  port 
  (
    addr  : in std_logic_vector (4 downto 0);
    data  : out std_logic_vector (3 downto 0)
  );

end entity;

architecture rtl of lightrom is
  -- definitions go here

begin

    -- Given instructions
    -- data <= 
    -- "0000" when addr = "00000" else -- move 0s to LR  00000000
    -- "0101" when addr = "00001" else -- bit invert LR  11111111
    -- "0101" when addr = "00010" else -- bit invert LR  00000000
    -- "0101" when addr = "00011" else -- bit invert LR  11111111
    -- "0001" when addr = "00100" else -- shift LR right 01111111
    -- "0001" when addr = "00101" else -- shift LR right 00111111
    -- "0111" when addr = "00110" else -- rotate LR left 01111110
    -- "0111" when addr = "00111" else -- rotate LR left 11111100
    -- "0111" when addr = "01000" else -- rotate LR left 11111001
    -- "0111" when addr = "01001" else -- rotate LR left 11110011
    -- "0010" when addr = "01010" else -- shift LR left  11100110
    -- "0010" when addr = "01011" else -- shift LR left  11001100
    -- "0011" when addr = "01100" else -- add 1 to LR    11001101
    -- "0100" when addr = "01101" else -- sub 1 from LR  11001100
    -- "0101" when addr = "01110" else -- bit invert LR  00110011
    -- "0011";                        -- add 1 to LR    0011010

    -- Custom instructions 1
    -- data <= 
    -- "0000" when addr = "00000" else -- move 0s to LR  00000000
    -- "0011" when addr = "00001" else -- add 1          00000001        
    -- "0111" when addr = "00010" else -- rotate left    00000010
    -- "0111" when addr = "00011" else -- rotate left    00000100
    -- "0111" when addr = "00100" else -- rotate left    00001000
    -- "0111" when addr = "00101" else -- rotate left    00010000
    -- "0111" when addr = "00110" else -- rotate LR left 00100000
    -- "0111" when addr = "00111" else -- rotate LR left 01000000
    -- "0111" when addr = "01000" else -- rotate LR left 10000000
    -- "0101" when addr = "01001" else -- invert bits    01111111
    -- "0001" when addr = "01010" else -- shift LR right 00111111
    -- "0001" when addr = "01011" else -- shift LR right 00011111
    -- "0001" when addr = "01100" else -- shift LR right 00001111
    -- "0101" when addr = "01101" else -- invert         11110000
    -- "0101" when addr = "01110" else -- bit invert LR  00001111
    -- "0000"; 

    -- Custom Instructions 2
    -- data <= 
    -- "0000" when addr = "00000" else -- move 0s to LR  00000000
    -- "0011" when addr = "00001" else -- add 1          00000001        
    -- "0011" when addr = "00010" else -- add 1          00000010
    -- "0011" when addr = "00011" else -- add 1          00000011
    -- "0011" when addr = "00100" else -- add 1          00000100
    -- "0101" when addr = "00101" else -- invert         11111011
    -- "0111" when addr = "00110" else -- rotate LR left 11110111
    -- "0100" when addr = "00111" else -- subtract 1     11110110
    -- "0101" when addr = "01000" else -- invert         00001001
    -- "0111" when addr = "01001" else -- shift left     00010010
    -- "0111" when addr = "01010" else -- shift LR left  00100100
    -- "0101" when addr = "01011" else -- invert         11011011
    -- "0101" when addr = "01100" else -- invert         00100100
    -- "0101" when addr = "01101" else -- invert         11011011
    -- "0101" when addr = "01110" else -- bit invert LR  00100100
    -- "0000"; 

    -- Custom Instructions 3 EXTENDED
    data <= 
    "0000" when addr = "00000" else -- move 0s to LR  00000000
    "0011" when addr = "00001" else -- add 1          00000001        
    "0111" when addr = "00010" else -- rotate left    00000010
    "0111" when addr = "00011" else -- rotate left    00000100
    "0111" when addr = "00100" else -- rotate left    00001000
    "0111" when addr = "00101" else -- rotate left    00010000
    "0111" when addr = "00110" else -- rotate LR left 00100000
    "0111" when addr = "00111" else -- rotate LR left 01000000
    "0111" when addr = "01000" else -- rotate LR left 10000000
    "0101" when addr = "01001" else -- invert bits    01111111
    "0001" when addr = "01010" else -- shift LR right 00111111
    "0001" when addr = "01011" else -- shift LR right 00011111
    "0001" when addr = "01100" else -- shift LR right 00001111
    "0101" when addr = "01101" else -- invert         11110000
    "0101" when addr = "01110" else -- bit invert LR  00001111
    "1101" when addr = "01111" else -- load alternate 10101010
    "0011" when addr = "10000" else -- add 1          10101011
    "1111" when addr = "10001" else -- rotate left 2  10101110
    "1111" when addr = "10010" else -- rotate left 2  10111010
    "1111" when addr = "10011" else -- rotate left 2  11101010
    "1000" when addr = "10100" else -- load full      11111111
    "1001" when addr = "10101" else -- shift right 2  00111111
    "1001" when addr = "10110" else -- shift right 2  00001111
    "1001" when addr = "10111" else -- shift right 2  00000011
    "0101" when addr = "11000" else -- invert         11111100
    "1100" when addr = "11001" else -- sub 2          11111010
    "1100" when addr = "11010" else -- sub 2          11111000
    "1100" when addr = "11011" else -- sub 2          11011000
    "1010" when addr = "11100" else -- shift left 2   11011000
    "1010" when addr = "11101" else -- shift left 2   01100000
    "0011" when addr = "11110" else -- add 1          10000001
    "0101"; 


end rtl;

classProjectStuff/232/Project4/task1/lights.vhd
-- Owen Goldthwaite
-- CS232

library ieee;
use ieee.std_logic_1164.all;
use ieee.numeric_std.all;

entity lights is

	port(
		clk		 : in	std_logic;
		reset	 : in	std_logic;
        lightsOut	 : out	std_logic_vector(7 downto 0);
        IRView	 : out	std_logic_vector(3 downto 0)      
	);

end entity;

architecture rtl of lights is

    component lightrom is
        port 
        (
          addr  : in std_logic_vector (4 downto 0);
          data  : out std_logic_vector (3 downto 0)
        );
    end component;

	-- Build an enumerated type for the state machine
	type state_type is (sFetch, sExecute);
	-- Register to hold the current state
    signal state   : state_type;
    -- Other signals
    signal IR : std_logic_vector(3 downto 0);
    signal PC : unsigned(4 downto 0);
    signal LR : unsigned(7 downto 0);
    signal ROMvalue : std_logic_vector(3 downto 0);

begin

	-- Logic to advance to the next state
	process (clk, reset)
	begin
        if reset = '0' then
            -- Resetting everything
            LR <= (others => '0'); 
            PC <= (others => '0');
            IR <= (others => '0');
            state <= sFetch;
		elsif (rising_edge(clk)) then
			case state is
				when sFetch=>
                    IR <= ROMvalue;
                    PC <= PC + 1;
                    state <= sExecute;
				when sExecute=>
                    case IR is -- Set of rules/instructions based on IR, extended to 4 bits
                        when "0000" => LR <= "00000000";
                        when "0001" => LR <= shift_right(LR, 1);
                        when "0010" => LR <= shift_left(LR, 1);
                        when "0011" => LR <= LR + 1;
                        when "0100" => LR <= LR - 1;
                        when "0101" => LR <= not LR;
                        when "0110" => LR <= rotate_right(LR,1);
                        when "0111" => LR <= rotate_left(LR,1);
                        when "1000" => LR <= "11111111";
                        when "1001" => LR <= shift_right(LR, 2);
                        when "1010" => LR <= shift_left(LR, 2); 
                        when "1011" => LR <= LR + 2;
                        when "1100" => LR <= LR - 2;
                        when "1101" => LR <= "10101010";
                        when "1110" => LR <= rotate_right(LR,2);
                        when "1111" => LR <= rotate_left(LR,2);
                        when others => LR <= "11111111";
                    end case;   
                    state <= sFetch;             
			end case;
		end if;
    end process;
    
    IRview <= IR;
    lightsOut <= std_logic_vector(LR);

    lightsrom1: lightrom port map(addr=>std_logic_vector(PC), data=>ROMvalue);

end rtl;


ghdl -c --ieee=synopsys -fexplicit --work=altera_mf C:\Users\Owen\Desktop\232 Stuff\altera_stuff\altera/*.vhd stackertest.vhd stacker.vhd memram_lab.vhd -r stackertest --vcd=stackertest.vcd

classProjectStuff/232/Project4/task1/lightsbench.vhd
-- Bruce A. Maxwell
-- Spring 2013
-- CS 232
--
-- test program for the lights circuit
--

library ieee;
use ieee.std_logic_1164.all;
use ieee.numeric_std.all;

entity lightsbench is
end entity;

architecture test of lightsbench is
  constant num_cycles : integer := 80; -- Changed to 80 cycles for longer programs

  -- this circuit just needs a clock and a reset
  signal clk : std_logic := '1';
  signal reset : std_logic;

  -- lights component
  component lights
    port(		
        clk		 : in	std_logic;
        reset	 : in	std_logic;
        lightsOut	 : out	std_logic_vector(7 downto 0);
        IRView	 : out	std_logic_vector(3 downto 0)
    );
  end component;

  -- output signals
  signal lightsig : std_logic_vector(7 downto 0);
  signal irview : std_logic_vector(3 downto 0);
  signal pcview : std_logic_vector(4 downto 0);

begin

  -- start off with a short reset
  reset <= '0', '1' after 5 ns;

  -- create a clock
  process begin
    for i in 1 to num_cycles loop
      clk <= not clk;
      wait for 5 ns;
      clk <= not clk;
      wait for 5 ns;
    end loop;
    wait;
  end process;

  -- port map the circuit
  L0: lights port map( clk, reset, lightsig, irview);

end test;

classProjectStuff/232/Project4/task1/lightsbench.vcd
$date
  Mon Oct 05 13:30:19 2020
$end
$version
  GHDL v0
$end
$timescale
  1 fs
$end
$scope module standard $end
$upscope $end
$scope module std_logic_1164 $end
$upscope $end
$scope module numeric_std $end
$upscope $end
$scope module lightsbench $end
$var reg 1 ! clk $end
$var reg 1 " reset $end
$var reg 8 # lightsig[7:0] $end
$var reg 4 $ irview[3:0] $end
$var reg 5 % pcview[4:0] $end
$scope module l0 $end
$var reg 1 & clk $end
$var reg 1 ' reset $end
$var reg 8 ( lightsout[7:0] $end
$var reg 4 ) irview[3:0] $end
$comment state is not handled $end
$var reg 4 * ir[3:0] $end
$var reg 5 + pc[4:0] $end
$var reg 8 , lr[7:0] $end
$var reg 4 - romvalue[3:0] $end
$scope module lightsrom1 $end
$var reg 5 . addr[4:0] $end
$var reg 4 / data[3:0] $end
$upscope $end
$upscope $end
$upscope $end
$enddefinitions $end
#0
0!
0"
b00000000 #
b0000 $
bUUUUU %
0&
0'
b00000000 (
b0000 )
b0000 *
b00000 +
b00000000 ,
b0000 -
b00000 .
b0000 /
#5000000
1!
1"
1&
1'
b00001 +
b0011 -
b00001 .
b0011 /
#10000000
0!
0&
#15000000
1!
1&
#20000000
0!
0&
#25000000
1!
b0011 $
1&
b0011 )
b0011 *
b00010 +
b0111 -
b00010 .
b0111 /
#30000000
0!
0&
#35000000
1!
b00000001 #
1&
b00000001 (
b00000001 ,
#40000000
0!
0&
#45000000
1!
b0111 $
1&
b0111 )
b0111 *
b00011 +
b00011 .
#50000000
0!
0&
#55000000
1!
b00000010 #
1&
b00000010 (
b00000010 ,
#60000000
0!
0&
#65000000
1!
1&
b00100 +
b00100 .
#70000000
0!
0&
#75000000
1!
b00000100 #
1&
b00000100 (
b00000100 ,
#80000000
0!
0&
#85000000
1!
1&
b00101 +
b00101 .
#90000000
0!
0&
#95000000
1!
b00001000 #
1&
b00001000 (
b00001000 ,
#100000000
0!
0&
#105000000
1!
1&
b00110 +
b00110 .
#110000000
0!
0&
#115000000
1!
b00010000 #
1&
b00010000 (
b00010000 ,
#120000000
0!
0&
#125000000
1!
1&
b00111 +
b00111 .
#130000000
0!
0&
#135000000
1!
b00100000 #
1&
b00100000 (
b00100000 ,
#140000000
0!
0&
#145000000
1!
1&
b01000 +
b01000 .
#150000000
0!
0&
#155000000
1!
b01000000 #
1&
b01000000 (
b01000000 ,
#160000000
0!
0&
#165000000
1!
1&
b01001 +
b0101 -
b01001 .
b0101 /
#170000000
0!
0&
#175000000
1!
b10000000 #
1&
b10000000 (
b10000000 ,
#180000000
0!
0&
#185000000
1!
b0101 $
1&
b0101 )
b0101 *
b01010 +
b0001 -
b01010 .
b0001 /
#190000000
0!
0&
#195000000
1!
b01111111 #
1&
b01111111 (
b01111111 ,
#200000000
0!
0&
#205000000
1!
b0001 $
1&
b0001 )
b0001 *
b01011 +
b01011 .
#210000000
0!
0&
#215000000
1!
b00111111 #
1&
b00111111 (
b00111111 ,
#220000000
0!
0&
#225000000
1!
1&
b01100 +
b01100 .
#230000000
0!
0&
#235000000
1!
b00011111 #
1&
b00011111 (
b00011111 ,
#240000000
0!
0&
#245000000
1!
1&
b01101 +
b0101 -
b01101 .
b0101 /
#250000000
0!
0&
#255000000
1!
b00001111 #
1&
b00001111 (
b00001111 ,
#260000000
0!
0&
#265000000
1!
b0101 $
1&
b0101 )
b0101 *
b01110 +
b01110 .
#270000000
0!
0&
#275000000
1!
b11110000 #
1&
b11110000 (
b11110000 ,
#280000000
0!
0&
#285000000
1!
1&
b01111 +
b1101 -
b01111 .
b1101 /
#290000000
0!
0&
#295000000
1!
b00001111 #
1&
b00001111 (
b00001111 ,
#300000000
0!
0&
#305000000
1!
b1101 $
1&
b1101 )
b1101 *
b10000 +
b0011 -
b10000 .
b0011 /
#310000000
0!
0&
#315000000
1!
b10101010 #
1&
b10101010 (
b10101010 ,
#320000000
0!
0&
#325000000
1!
b0011 $
1&
b0011 )
b0011 *
b10001 +
b1111 -
b10001 .
b1111 /
#330000000
0!
0&
#335000000
1!
b10101011 #
1&
b10101011 (
b10101011 ,
#340000000
0!
0&
#345000000
1!
b1111 $
1&
b1111 )
b1111 *
b10010 +
b10010 .
#350000000
0!
0&
#355000000
1!
b10101110 #
1&
b10101110 (
b10101110 ,
#360000000
0!
0&
#365000000
1!
1&
b10011 +
b10011 .
#370000000
0!
0&
#375000000
1!
b10111010 #
1&
b10111010 (
b10111010 ,
#380000000
0!
0&
#385000000
1!
1&
b10100 +
b1000 -
b10100 .
b1000 /
#390000000
0!
0&
#395000000
1!
b11101010 #
1&
b11101010 (
b11101010 ,
#400000000
0!
0&
#405000000
1!
b1000 $
1&
b1000 )
b1000 *
b10101 +
b1001 -
b10101 .
b1001 /
#410000000
0!
0&
#415000000
1!
b11111111 #
1&
b11111111 (
b11111111 ,
#420000000
0!
0&
#425000000
1!
b1001 $
1&
b1001 )
b1001 *
b10110 +
b10110 .
#430000000
0!
0&
#435000000
1!
b00111111 #
1&
b00111111 (
b00111111 ,
#440000000
0!
0&
#445000000
1!
1&
b10111 +
b10111 .
#450000000
0!
0&
#455000000
1!
b00001111 #
1&
b00001111 (
b00001111 ,
#460000000
0!
0&
#465000000
1!
1&
b11000 +
b0101 -
b11000 .
b0101 /
#470000000
0!
0&
#475000000
1!
b00000011 #
1&
b00000011 (
b00000011 ,
#480000000
0!
0&
#485000000
1!
b0101 $
1&
b0101 )
b0101 *
b11001 +
b1100 -
b11001 .
b1100 /
#490000000
0!
0&
#495000000
1!
b11111100 #
1&
b11111100 (
b11111100 ,
#500000000
0!
0&
#505000000
1!
b1100 $
1&
b1100 )
b1100 *
b11010 +
b11010 .
#510000000
0!
0&
#515000000
1!
b11111010 #
1&
b11111010 (
b11111010 ,
#520000000
0!
0&
#525000000
1!
1&
b11011 +
b11011 .
#530000000
0!
0&
#535000000
1!
b11111000 #
1&
b11111000 (
b11111000 ,
#540000000
0!
0&
#545000000
1!
1&
b11100 +
b1010 -
b11100 .
b1010 /
#550000000
0!
0&
#555000000
1!
b11110110 #
1&
b11110110 (
b11110110 ,
#560000000
0!
0&
#565000000
1!
b1010 $
1&
b1010 )
b1010 *
b11101 +
b11101 .
#570000000
0!
0&
#575000000
1!
b11011000 #
1&
b11011000 (
b11011000 ,
#580000000
0!
0&
#585000000
1!
1&
b11110 +
b0011 -
b11110 .
b0011 /
#590000000
0!
0&
#595000000
1!
b01100000 #
1&
b01100000 (
b01100000 ,
#600000000
0!
0&
#605000000
1!
b0011 $
1&
b0011 )
b0011 *
b11111 +
b0101 -
b11111 .
b0101 /
#610000000
0!
0&
#615000000
1!
b01100001 #
1&
b01100001 (
b01100001 ,
#620000000
0!
0&
#625000000
1!
b0101 $
1&
b0101 )
b0101 *
b00000 +
b0000 -
b00000 .
b0000 /
#630000000
0!
0&
#635000000
1!
b10011110 #
1&
b10011110 (
b10011110 ,
#640000000
0!
0&
#645000000
1!
b0000 $
1&
b0000 )
b0000 *
b00001 +
b0011 -
b00001 .
b0011 /
#650000000
0!
0&
#655000000
1!
b00000000 #
1&
b00000000 (
b00000000 ,
#660000000
0!
0&
#665000000
1!
b0011 $
1&
b0011 )
b0011 *
b00010 +
b0111 -
b00010 .
b0111 /
#670000000
0!
0&
#675000000
1!
b00000001 #
1&
b00000001 (
b00000001 ,
#680000000
0!
0&
#685000000
1!
b0111 $
1&
b0111 )
b0111 *
b00011 +
b00011 .
#690000000
0!
0&
#695000000
1!
b00000010 #
1&
b00000010 (
b00000010 ,
#700000000
0!
0&
#705000000
1!
1&
b00100 +
b00100 .
#710000000
0!
0&
#715000000
1!
b00000100 #
1&
b00000100 (
b00000100 ,
#720000000
0!
0&
#725000000
1!
1&
b00101 +
b00101 .
#730000000
0!
0&
#735000000
1!
b00001000 #
1&
b00001000 (
b00001000 ,
#740000000
0!
0&
#745000000
1!
1&
b00110 +
b00110 .
#750000000
0!
0&
#755000000
1!
b00010000 #
1&
b00010000 (
b00010000 ,
#760000000
0!
0&
#765000000
1!
1&
b00111 +
b00111 .
#770000000
0!
0&
#775000000
1!
b00100000 #
1&
b00100000 (
b00100000 ,
#780000000
0!
0&
#785000000
1!
1&
b01000 +
b01000 .
#790000000
0!
0&
#795000000
1!
b01000000 #
1&
b01000000 (
b01000000 ,
